CHANGES.txt
MANIFEST.in
README.txt
old_ChangeLog
setup.py
debian/README.Debian
debian/changelog
debian/compat
debian/control
debian/copyright
debian/docs
debian/rules
docs/CREDITS.txt
docs/INSTALL.rst
docs/LICENSE.txt
docs/README.txt
docs/TODO.txt
docs/logo.svg
docs/logo64x64.png
docs/taggedvalues-argouml.png
docs/manual/1.1-introduction.stx
docs/manual/1.2-installation.stx
docs/manual/1.3-uml.stx
docs/manual/1.4-helloworld.stx
docs/manual/2.1-classes.stx
docs/manual/2.2-attributes-fields.stx
docs/manual/2.3-widgets.stx
docs/manual/2.4-methods-actions.stx
docs/manual/2.5-relationships.stx
docs/manual/2.6-workflow.stx
docs/manual/3.1-vocabulary-manager.stx
docs/manual/3.2-relations.stx
docs/manual/3.3-remember.stx
docs/manual/3.4-compoundarrayfields.stx
docs/manual/4.1-quickref.stx
docs/manual/4.2-taggedvalues.stx
docs/manual/4.3-stereotypes.stx
docs/manual/5.1-argouml-setup.stx
docs/manual/countries.vdex
docs/manual/helloworld-plone-shot.png
docs/manual/helloworld.png
docs/manual/helloworld3.zargo
docs/manual/taggedvalues-argouml.png
docs/manual/uml-model-small.png
docs/manual/workflow.jpg
docs/samples/README.txt
docs/samples/RelationsSample.zuml
docs/samples/SampleTestcase.zuml
docs/samples/SampleWorkflows.zargo
docs/samples/SimpleSample.xmi
docs/samples/adapters-and-schemaextenders.zargo
docs/samples/browserview.zargo
docs/samples/plonehrm.zargo
src/archgenxml/ArchGenXML.py
src/archgenxml/ArchetypesGenerator.py
src/archgenxml/ArgoUMLProfileGenerator.py
src/archgenxml/BaseGenerator.py
src/archgenxml/CodeSectionHandler.py
src/archgenxml/OptionParser.py
src/archgenxml/PyParser.py
src/archgenxml/TaggedValueSupport.py
src/archgenxml/UMLProfile.py
src/archgenxml/WorkflowGenerator.py
src/archgenxml/__init__.py
src/archgenxml/atmaps.py
src/archgenxml/atumlprofile.py
src/archgenxml/codesnippets.py
src/archgenxml/find-all-types
src/archgenxml/interfaces.py
src/archgenxml/loginitializer.py
src/archgenxml/patches.py
src/archgenxml/utility.py
src/archgenxml/utils.py
src/archgenxml.egg-info/PKG-INFO
src/archgenxml.egg-info/SOURCES.txt
src/archgenxml.egg-info/dependency_links.txt
src/archgenxml.egg-info/entry_points.txt
src/archgenxml.egg-info/not-zip-safe
src/archgenxml.egg-info/requires.txt
src/archgenxml.egg-info/top_level.txt
