Metadata-Version: 1.1
Name: archgenxml
Version: 2.7
Summary: UML to code generator for Plone
Home-page: http://plone.org/products/archgenxml
Author: Phil Auersperg, Jens Klein, et al
Author-email: dev@bluedynamics.com
License: GPL
Keywords: zope plone UML generator
Platform: UNKNOWN
Classifier: Programming Language :: Python
Classifier: License :: OSI Approved :: GNU General Public License (GPL)
Classifier: Operating System :: OS Independent
Classifier: Topic :: Software Development :: Code Generators
Classifier: Framework :: Zope2
Classifier: Framework :: Plone
